seavoice_sdk/__init__.py
seavoice_sdk/audio.py
seavoice_sdk/logger.py
seavoice_sdk/speech.py
seavoice_sdk/utils.py
seavoice_sdk-0.2.17.dist-info/LICENSE
seavoice_sdk-0.2.17.dist-info/METADATA
seavoice_sdk-0.2.17.dist-info/WHEEL
seavoice_sdk-0.2.17.dist-info/top_level.txt
seavoice_sdk-0.2.17.dist-info/RECORD
