Metadata-Version: 2.1
Name: seavoice-sdk
Version: 0.2.17
Summary: SeaVoice SDK: Client for Seasalt speech recognition and speech synthesis.
Home-page: UNKNOWN
Author: Seasalt.ai
Author-email: info@seasalt.ai
License: UNKNOWN
Platform: UNKNOWN
Classifier: Programming Language :: Python :: 3
Classifier: License :: OSI Approved :: MIT License
Classifier: Operating System :: OS Independent
Requires-Python: >=3.6
License-File: LICENSE
Requires-Dist: websocket-client (==0.57.0)
Requires-Dist: websockets (>=8.1)
Requires-Dist: ws4py (==0.5.1)
